great_assertions.py
src/__init__.py
src/ga_dataframe.py
src/ga_pandas.py
src/ga_spark.py
src/utils.py
great_assertions-0.0.75.dist-info/LICENSE
great_assertions-0.0.75.dist-info/METADATA
great_assertions-0.0.75.dist-info/WHEEL
great_assertions-0.0.75.dist-info/entry_points.txt
great_assertions-0.0.75.dist-info/top_level.txt
great_assertions-0.0.75.dist-info/zip-safe
great_assertions-0.0.75.dist-info/RECORD
